{"cameraMode":{"drawMode":0,"name":"Shaded","section":"Shading Mode"},"sceneLighting":true,"audioPlay":false,"sceneViewState":{"showFog":true,"showMaterialUpdate":false,"showSkybox":true,"showFlares":true,"showImageEffects":true,"showParticleSystems":true},"in2DMode":false,"pivot":{"x":1.2053996324539185,"y":-2.8612890243530275,"z":13.324939727783204},"rotation":{"x":0.0008241563336923718,"y":0.9523609280586243,"z":-0.3049613833427429,"w":0.0025749653577804567},"size":63.70357131958008,"orthographic":false}